xyz_web3/__init__.py
xyz_web3/admin.py
xyz_web3/apis.py
xyz_web3/apps.py
xyz_web3/browse_client.py
xyz_web3/choices.py
xyz_web3/cron.py
xyz_web3/helper.py
xyz_web3/models.py
xyz_web3/receivers.py
xyz_web3/serializers.py
xyz_web3/stats.py
xyz_web3/stores.py
xyz_web3/migrations/0001_initial.py
xyz_web3/migrations/0002_auto_20220615_1425.py
xyz_web3/migrations/0003_auto_20220616_1411.py
xyz_web3/migrations/0004_auto_20220619_1714.py
xyz_web3/migrations/0005_auto_20220623_1114.py
xyz_web3/migrations/0006_auto_20220627_1743.py
xyz_web3/migrations/0007_auto_20220706_1424.py
xyz_web3/migrations/0008_auto_20220706_1644.py
xyz_web3/migrations/__init__.py
xyz_web3-0.1.17.dist-info/METADATA
xyz_web3-0.1.17.dist-info/WHEEL
xyz_web3-0.1.17.dist-info/top_level.txt
xyz_web3-0.1.17.dist-info/RECORD
